{
  "version" : "today-summary-v1",
  "kospi_today" : "2419.29",
  "kospi_diff" : "-32.77",
  "featured_today" : [
    { "name":"현대글로비스", "id":"086280", "volumeInc":"8.13", "price":"173500", "priceInc":"10.16" },
    { "name":"현대모비스", "id":"012330", "volumeInc":"5.24", "price":"261500", "priceInc":"6.73" },
    { "name":"현대엘리베이", "id":"017800", "volumeInc":"5.24", "price":"80000", "priceInc":"2.56" },
    { "name":"쌍용양회", "id":"003410", "volumeInc":"3.07", "price":"23850", "priceInc":"6.00" },
    { "name":"한국단자", "id":"025540", "volumeInc":"2.33", "price":"54300", "priceInc":"0.37" },
    { "name":"현대위아", "id":"011210", "volumeInc":"2.32", "price":"58000", "priceInc":"3.76" },
    { "name":"대상", "id":"001680", "volumeInc":"2.28", "price":"25600", "priceInc":"4.07" },
    { "name":"현대건설", "id":"000720", "volumeInc":"2.25", "price":"42700", "priceInc":"4.02" },
    { "name":"잇츠한불", "id":"226320", "volumeInc":"1.98", "price":"71000", "priceInc":"4.41" },
    { "name":"기아차", "id":"000270", "volumeInc":"1.97", "price":"33000", "priceInc":"3.94" },
    { "name":"태광산업", "id":"003240", "volumeInc":"1.91", "price":"1255000", "priceInc":"4.41" },
    { "name":"한국콜마", "id":"161890", "volumeInc":"1.79", "price":"78400", "priceInc":"0.77" }
  ],
  "holdings_today" : [
    { "name":"두산우", "id":"000155", "holdings":"71734" },
    { "name":"한국쉘석유", "id":"002960", "holdings":"5955507" },
    { "name":"성보화학", "id":"003080", "holdings":"385890" },
    { "name":"코리안리", "id":"003690", "holdings":"523749" },
    { "name":"효성", "id":"004800", "holdings":"2923051" },
    { "name":"현대차우", "id":"005385", "holdings":"286584" },
    { "name":"미래에셋대우우", "id":"006805", "holdings":"309255" },
    { "name":"미래에셋대우2우B", "id":"00680K", "holdings":"63740" },
    { "name":"대덕전자", "id":"008060", "holdings":"1674697" },
    { "name":"한샘", "id":"009240", "holdings":"320500" },
    { "name":"S-Oil", "id":"010950", "holdings":"115500" },
    { "name":"S-Oil우", "id":"010955", "holdings":"2854370" },
    { "name":"한국전력", "id":"015760", "holdings":"696000" },
    { "name":"SK텔레콤", "id":"017670", "holdings":"1485000" },
    { "name":"SK가스", "id":"018670", "holdings":"384000" },
    { "name":"대교", "id":"019680", "holdings":"758314" },
    { "name":"대교우B", "id":"019685", "holdings":"300075" },
    { "name":"코웨이", "id":"021240", "holdings":"939400" },
    { "name":"삼성카드", "id":"029780", "holdings":"190500" },
    { "name":"KT", "id":"030200", "holdings":"2351684" },
    { "name":"KT&G", "id":"033780", "holdings":"517800" },
    { "name":"맥쿼리인프라", "id":"088980", "holdings":"658465" },
    { "name":"CJ제일제당 우", "id":"097955", "holdings":"286500" },
    { "name":"코오롱인더", "id":"120110", "holdings":"216500" },
    { "name":"TIGER 레버리지", "id":"123320", "holdings":"3530144" },
    { "name":"TIGER 200 금융", "id":"139270", "holdings":"26525" },
    { "name":"광주은행", "id":"192530", "holdings":"58150" }
  ],
  "holdings_diff" : [
    { "name":"두산우", "id":"000155", "diff":"-71733" },
    { "name":"미래에셋대우우", "id":"006805", "diff":"4960" },
    { "name":"미래에셋대우2우B", "id":"00680K", "diff":"4490" },
    { "name":"SK가스", "id":"018670", "diff":"91700" },
    { "name":"맥쿼리인프라", "id":"088980", "diff":"-33340" },
    { "name":"광주은행", "id":"192530", "diff":"11150" }
  ]
}
