{
  "version" : "volume-featured-profit-v1",
  "stocks" : [
    { "name":"한미사이언스", "id":"008930", "profit":"29.99", "featuredDate":"2017-11-01", "featuredVolumeInc":"1.94" },
    { "name":"경동나비엔", "id":"009450", "profit":"28.70", "featuredDate":"2017-11-01", "featuredVolumeInc":"2.29" },
    { "name":"제일약품", "id":"002620", "profit":"23.42", "featuredDate":"2017-11-07", "featuredVolumeInc":"2.37" },
    { "name":"한미약품", "id":"128940", "profit":"23.01", "featuredDate":"2017-11-01", "featuredVolumeInc":"2.37" },
    { "name":"쌍용양회", "id":"003410", "profit":"21.86", "featuredDate":"2017-11-01", "featuredVolumeInc":"1.71" },
    { "name":"JW홀딩스", "id":"096760", "profit":"20.35", "featuredDate":"2017-11-01", "featuredVolumeInc":"2.19" },
    { "name":"키움증권", "id":"039490", "profit":"19.13", "featuredDate":"2017-11-09", "featuredVolumeInc":"1.63" },
    { "name":"JW중외제약", "id":"001060", "profit":"17.62", "featuredDate":"2017-11-01", "featuredVolumeInc":"5.40" },
    { "name":"대웅제약", "id":"069620", "profit":"17.55", "featuredDate":"2017-11-03", "featuredVolumeInc":"1.66" },
    { "name":"영진약품", "id":"003520", "profit":"17.02", "featuredDate":"2017-11-06", "featuredVolumeInc":"1.60" },
    { "name":"종근당", "id":"185750", "profit":"16.95", "featuredDate":"2017-11-03", "featuredVolumeInc":"1.73" },
    { "name":"부광약품", "id":"003000", "profit":"15.75", "featuredDate":"2017-11-03", "featuredVolumeInc":"2.49" },
    { "name":"동아에스티", "id":"170900", "profit":"15.43", "featuredDate":"2017-11-02", "featuredVolumeInc":"5.91" },
    { "name":"하나투어", "id":"039130", "profit":"14.69", "featuredDate":"2017-11-02", "featuredVolumeInc":"3.54" },
    { "name":"GKL", "id":"114090", "profit":"14.59", "featuredDate":"2017-11-07", "featuredVolumeInc":"1.81" },
    { "name":"일양약품", "id":"007570", "profit":"13.28", "featuredDate":"2017-11-03", "featuredVolumeInc":"1.60" },
    { "name":"녹십자", "id":"006280", "profit":"13.13", "featuredDate":"2017-11-03", "featuredVolumeInc":"1.87" },
    { "name":"삼성중공업", "id":"010140", "profit":"12.61", "featuredDate":"2017-11-03", "featuredVolumeInc":"1.76" },
    { "name":"대림산업", "id":"000210", "profit":"11.75", "featuredDate":"2017-11-01", "featuredVolumeInc":"1.55" },
    { "name":"오리온", "id":"001800", "profit":"11.28", "featuredDate":"2017-11-03", "featuredVolumeInc":"2.33" },
    { "name":"잇츠스킨", "id":"226320", "profit":"10.86", "featuredDate":"2017-11-06", "featuredVolumeInc":"2.55" },
    { "name":"유한양행", "id":"000100", "profit":"10.44", "featuredDate":"2017-11-01", "featuredVolumeInc":"2.02" },
    { "name":"CJ제일제당", "id":"097950", "profit":"10.40", "featuredDate":"2017-11-03", "featuredVolumeInc":"1.99" },
    { "name":"GS리테일", "id":"007070", "profit":"10.06", "featuredDate":"2017-11-07", "featuredVolumeInc":"4.03" },
    { "name":"NHN엔터테인먼트", "id":"181710", "profit":"9.29", "featuredDate":"2017-11-10", "featuredVolumeInc":"1.58" },
    { "name":"태광산업", "id":"003240", "profit":"9.23", "featuredDate":"2017-11-03", "featuredVolumeInc":"1.70" },
    { "name":"LG상사", "id":"001120", "profit":"8.92", "featuredDate":"2017-11-02", "featuredVolumeInc":"1.68" },
    { "name":"호텔신라", "id":"008770", "profit":"8.65", "featuredDate":"2017-11-06", "featuredVolumeInc":"1.86" },
    { "name":"한국가스공사", "id":"036460", "profit":"8.62", "featuredDate":"2017-11-07", "featuredVolumeInc":"1.98" },
    { "name":"동원F&B", "id":"049770", "profit":"8.46", "featuredDate":"2017-11-07", "featuredVolumeInc":"1.88" },
    { "name":"지역난방공사", "id":"071320", "profit":"8.12", "featuredDate":"2017-11-03", "featuredVolumeInc":"2.46" },
    { "name":"KT&G", "id":"033780", "profit":"7.73", "featuredDate":"2017-11-06", "featuredVolumeInc":"2.11" },
    { "name":"신세계", "id":"004170", "profit":"7.63", "featuredDate":"2017-11-07", "featuredVolumeInc":"3.59" },
    { "name":"강원랜드", "id":"035250", "profit":"7.62", "featuredDate":"2017-11-09", "featuredVolumeInc":"2.98" },
    { "name":"한섬", "id":"020000", "profit":"7.55", "featuredDate":"2017-11-08", "featuredVolumeInc":"3.16" },
    { "name":"SKC", "id":"011790", "profit":"7.49", "featuredDate":"2017-11-09", "featuredVolumeInc":"1.65" },
    { "name":"CJ", "id":"001040", "profit":"7.43", "featuredDate":"2017-11-03", "featuredVolumeInc":"1.93" },
    { "name":"한화케미칼", "id":"009830", "profit":"7.42", "featuredDate":"2017-11-01", "featuredVolumeInc":"1.73" },
    { "name":"삼립식품", "id":"005610", "profit":"7.38", "featuredDate":"2017-11-10", "featuredVolumeInc":"2.83" },
    { "name":"롯데정밀화학", "id":"004000", "profit":"7.16", "featuredDate":"2017-11-01", "featuredVolumeInc":"5.55" }
  ]
}
