{
  "version" : "volume-featured-days-v1",
  "name" : "코스맥스",
  "dailyTrading" : [
    { "date":"2017-04-03", "volume":"69924", "adjClosePrice":"139000", "featured":false },
    { "date":"2017-04-04", "volume":"117561", "adjClosePrice":"142000", "featured":false },
    { "date":"2017-04-05", "volume":"87915", "adjClosePrice":"140000", "featured":false },
    { "date":"2017-04-06", "volume":"41333", "adjClosePrice":"138000", "featured":false },
    { "date":"2017-04-07", "volume":"52761", "adjClosePrice":"138500", "featured":false },
    { "date":"2017-04-10", "volume":"73000", "adjClosePrice":"134500", "featured":false },
    { "date":"2017-04-11", "volume":"37117", "adjClosePrice":"134500", "featured":false },
    { "date":"2017-04-12", "volume":"65828", "adjClosePrice":"132500", "featured":false },
    { "date":"2017-04-13", "volume":"143475", "adjClosePrice":"138500", "featured":true },
    { "date":"2017-04-14", "volume":"46187", "adjClosePrice":"138000", "featured":false },
    { "date":"2017-04-17", "volume":"123591", "adjClosePrice":"142500", "featured":false }
  ]
}
