{
  "version" : "volume-featured-days-v1",
  "name" : "롯데정밀화학",
  "dailyTrading" : [
    { "date":"2017-07-12", "volume":"57572", "adjClosePrice":"40550", "featured":false },
    { "date":"2017-07-13", "volume":"82697", "adjClosePrice":"40200", "featured":false },
    { "date":"2017-07-14", "volume":"364775", "adjClosePrice":"43000", "featured":true },
    { "date":"2017-07-17", "volume":"124614", "adjClosePrice":"42800", "featured":false },
    { "date":"2017-07-18", "volume":"124852", "adjClosePrice":"42900", "featured":false },
    { "date":"2017-07-19", "volume":"84908", "adjClosePrice":"42550", "featured":false },
    { "date":"2017-07-20", "volume":"107057", "adjClosePrice":"42750", "featured":false },
    { "date":"2017-07-21", "volume":"78438", "adjClosePrice":"42150", "featured":false },
    { "date":"2017-07-24", "volume":"59438", "adjClosePrice":"42050", "featured":false },
    { "date":"2017-07-25", "volume":"83838", "adjClosePrice":"41850", "featured":false },
    { "date":"2017-07-26", "volume":"61933", "adjClosePrice":"42350", "featured":false }
  ]
}
