{
  "version" : "volume-featured-days-v1",
  "name" : "LG화학우",
  "dailyTrading" : [
    { "date":"2017-08-31", "volume":"30801", "adjClosePrice":"263000", "featured":false },
    { "date":"2017-09-01", "volume":"9900", "adjClosePrice":"260000", "featured":false },
    { "date":"2017-09-04", "volume":"11346", "adjClosePrice":"258500", "featured":false },
    { "date":"2017-09-05", "volume":"12308", "adjClosePrice":"254500", "featured":false },
    { "date":"2017-09-06", "volume":"14391", "adjClosePrice":"256500", "featured":false },
    { "date":"2017-09-07", "volume":"10016", "adjClosePrice":"253500", "featured":false },
    { "date":"2017-09-08", "volume":"9420", "adjClosePrice":"253500", "featured":false },
    { "date":"2017-09-11", "volume":"46081", "adjClosePrice":"265000", "featured":true },
    { "date":"2017-09-12", "volume":"24382", "adjClosePrice":"265000", "featured":false },
    { "date":"2017-09-13", "volume":"31321", "adjClosePrice":"276000", "featured":true },
    { "date":"2017-09-14", "volume":"32335", "adjClosePrice":"275000", "featured":false }
  ]
}
