{
  "version" : "volume-featured-days-v1",
  "name" : "현대엘리베이",
  "dailyTrading" : [
    { "date":"2018-03-07", "volume":"1581405", "adjClosePrice":"62600", "featured":true },
    { "date":"2018-03-08", "volume":"609125", "adjClosePrice":"64100", "featured":false },
    { "date":"2018-03-09", "volume":"3098169", "adjClosePrice":"78600", "featured":true },
    { "date":"2018-03-12", "volume":"1366118", "adjClosePrice":"75500", "featured":false },
    { "date":"2018-03-13", "volume":"715184", "adjClosePrice":"75900", "featured":false },
    { "date":"2018-03-14", "volume":"376187", "adjClosePrice":"74800", "featured":false },
    { "date":"2018-03-15", "volume":"443441", "adjClosePrice":"73300", "featured":false },
    { "date":"2018-03-16", "volume":"362463", "adjClosePrice":"74700", "featured":false },
    { "date":"2018-03-19", "volume":"1745416", "adjClosePrice":"84500", "featured":true },
    { "date":"2018-03-20", "volume":"780929", "adjClosePrice":"80200", "featured":false },
    { "date":"2018-03-21", "volume":"822961", "adjClosePrice":"80000", "featured":false }
  ]
}
