{
  "version" : "volume-featured-days-v1",
  "name" : "현대중공업",
  "dailyTrading" : [
    { "date":"2018-03-29", "volume":"528823", "adjClosePrice":"137500", "featured":false },
    { "date":"2018-03-30", "volume":"758917", "adjClosePrice":"132000", "featured":false },
    { "date":"2018-04-02", "volume":"543532", "adjClosePrice":"126000", "featured":false },
    { "date":"2018-04-03", "volume":"306758", "adjClosePrice":"126000", "featured":false },
    { "date":"2018-04-04", "volume":"406961", "adjClosePrice":"121000", "featured":false },
    { "date":"2018-04-05", "volume":"612104", "adjClosePrice":"129500", "featured":true },
    { "date":"2018-04-06", "volume":"204520", "adjClosePrice":"128000", "featured":false },
    { "date":"2018-04-09", "volume":"212181", "adjClosePrice":"126500", "featured":false },
    { "date":"2018-04-10", "volume":"206747", "adjClosePrice":"125500", "featured":false },
    { "date":"2018-04-11", "volume":"206316", "adjClosePrice":"126000", "featured":false },
    { "date":"2018-04-12", "volume":"353177", "adjClosePrice":"129000", "featured":false }
  ]
}
